lnqtools/__init__.py
lnqtools/mymodule.py
lnqtools-0.2.0.dist-info/METADATA
lnqtools-0.2.0.dist-info/WHEEL
lnqtools-0.2.0.dist-info/top_level.txt
lnqtools-0.2.0.dist-info/RECORD
