Metadata-Version: 2.1
Name: lnqtools
Version: 0.2.0
Summary: A simple package for adding and multiplying numbers
Home-page: https://github.com/yourusername/your_project
Author: LyNgocQue
Author-email: your_email@example.com
Classifier: Programming Language :: Python :: 3
Classifier: License :: OSI Approved :: MIT License
Classifier: Operating System :: OS Independent
Requires-Python: >=3.6
